data/__init__.py
data/base.py
data/content_type.py
data/lemmy_facade.py
data/matrix_facade.py
data/report_persistence.py
lemmyreportmessenger-0.2.0.dist-info/LICENSE.md
lemmyreportmessenger-0.2.0.dist-info/METADATA
lemmyreportmessenger-0.2.0.dist-info/WHEEL
lemmyreportmessenger-0.2.0.dist-info/top_level.txt
lemmyreportmessenger-0.2.0.dist-info/RECORD
